zzgui/__init__.py
zzgui/__main__.py
zzgui/qt5/__init__.py
zzgui/qt5/widgets/__init__.py
zzgui/qt5/widgets/zzbutton.py
zzgui/qt5/widgets/zzcheck.py
zzgui/qt5/widgets/zzcode.py
zzgui/qt5/widgets/zzcombo.py
zzgui/qt5/widgets/zzdate.py
zzgui/qt5/widgets/zzdoublespin.py
zzgui/qt5/widgets/zzframe.py
zzgui/qt5/widgets/zzgrid.py
zzgui/qt5/widgets/zzlabel.py
zzgui/qt5/widgets/zzline.py
zzgui/qt5/widgets/zzlist.py
zzgui/qt5/widgets/zzlookup.py
zzgui/qt5/widgets/zzprogressbar.py
zzgui/qt5/widgets/zzradio.py
zzgui/qt5/widgets/zzrelation.py
zzgui/qt5/widgets/zzscroller.py
zzgui/qt5/widgets/zzsheet.py
zzgui/qt5/widgets/zzspace.py
zzgui/qt5/widgets/zzspin.py
zzgui/qt5/widgets/zztab.py
zzgui/qt5/widgets/zztext.py
zzgui/qt5/widgets/zztoolbar.py
zzgui/qt5/widgets/zztoolbutton.py
zzgui/qt5/zzapp.py
zzgui/qt5/zzform.py
zzgui/qt5/zzmodel.py
zzgui/qt5/zzwidget.py
zzgui/qt5/zzwindow.py
zzgui/zzapp.py
zzgui/zzdialogs.py
zzgui/zzform.py
zzgui/zzmodel.py
zzgui/zzutils.py
zzgui/zzwidget.py
zzgui/zzwindow.py
zzgui-0.1.18.dist-info/LICENSE
zzgui-0.1.18.dist-info/WHEEL
zzgui-0.1.18.dist-info/METADATA
zzgui-0.1.18.dist-info/RECORD
