Metadata-Version: 2.1
Name: zzgui
Version: 0.1.18
Summary: Python GUI toolkit
License: Apache 2.0
Author: Andrei Puchko
Author-email: andrei.puchko@gmx.de
Requires-Python: >=3.7,<3.11
Classifier: License :: Other/Proprietary License
Classifier: Programming Language :: Python :: 3
Classifier: Programming Language :: Python :: 3.10
Classifier: Programming Language :: Python :: 3.7
Classifier: Programming Language :: Python :: 3.8
Classifier: Programming Language :: Python :: 3.9
Requires-Dist: PyQt5 (>=5.15.6,<6.0.0)
Requires-Dist: QScintilla (>=2.13.1,<3.0.0)
Requires-Dist: zzdb (>=0.1.11,<0.2.0)
